carduus/__init__.py
carduus/cli.py
carduus/keys.py
carduus/token/__init__.py
carduus/token/_impl.py
carduus/token/crypto.py
carduus/token/pii.py
carduus-0.4.1.dist-info/METADATA
carduus-0.4.1.dist-info/WHEEL
carduus-0.4.1.dist-info/entry_points.txt
carduus-0.4.1.dist-info/licenses/LICENSE
carduus-0.4.1.dist-info/RECORD
