Metadata-Version: 2.4
Name: carduus
Version: 0.4.1
Summary: PySpark implementation of the Open Privacy Preserving Record Linkage protocol.
License-File: LICENSE
Author: Eddie Pantridge
Author-email: eddie@spindlehealth.com
Requires-Python: >=3.10
Classifier: Programming Language :: Python :: 3
Classifier: Programming Language :: Python :: 3.10
Classifier: Programming Language :: Python :: 3.11
Classifier: Programming Language :: Python :: 3.12
Classifier: Programming Language :: Python :: 3.13
Classifier: Programming Language :: Python :: 3.14
Requires-Dist: click (>=8.1.8,<9.0.0)
Requires-Dist: cryptography (>=44.0.1,<45.0.0)
Requires-Dist: jellyfish (>=1.0.3,<2.0.0)
Requires-Dist: pyspark (>=3.5.0,<4.0.0)
